cfn_lint_serverless/__init__.py
cfn_lint_serverless/utils.py
cfn_lint_serverless/rules/__init__.py
cfn_lint_serverless/rules/api_gateway.py
cfn_lint_serverless/rules/appsync.py
cfn_lint_serverless/rules/eventbridge.py
cfn_lint_serverless/rules/lambda_.py
cfn_lint_serverless/rules/sns.py
cfn_lint_serverless/rules/sqs.py
cfn_lint_serverless/rules/step_functions.py
cfn_lint_serverless-0.3.3.dist-info/METADATA
cfn_lint_serverless-0.3.3.dist-info/WHEEL
cfn_lint_serverless-0.3.3.dist-info/RECORD
