Metadata-Version: 2.4
Name: cfn_lint_serverless
Version: 0.3.3
Summary: Serverless rules for cfn-lint
Author: Amazon Web Service
License-Expression: MIT-0
Requires-Python: <4,>=3.9.1
Requires-Dist: cfn-lint>=1.33.0
